[
  {
    "inputs": [],
    "name": "deposit",
    "outputs": [],
    "stateMutability": "payable",
    "type": "function"
  },
  {
    "inputs": [
      { "name": "_spender", "type": "address" },
      { "name": "_value", "type": "uint256" }
    ],
    "name": "approve",
    "outputs": [
      { "name": "", "type": "bool" }
    ],
    "stateMutability": "nonpayable",
    "type": "function"
  },
  {
    "inputs": [
      { "name": "_owner", "type": "address" },
      { "name": "_spender", "type": "address" }
    ],
    "name": "allowance",
    "outputs": [
      { "name": "", "type": "uint256" }
    ],
    "stateMutability": "view",
    "type": "function"
  },
  {
    "inputs": [
      { "name": "_owner", "type": "address" }
    ],
    "name": "balanceOf",
    "outputs": [
      { "name": "", "type": "uint256" }
    ],
    "stateMutability": "view",
    "type": "function"
  }
]
